Workbook

Sheet Inputs
A1: Names | B1: Values
A2: Base Type | B2: 100
A3: Base demand | B3: 1000
A4: Elasticity | B4: -1.5
A5: Variable Cost | B5: 40
A6: Fixed cost | B6: 20000
A7: Demand Slope | B7: 7

Sheet Model
A1: Price | B1: 141.42857
A2: Demand | B2: =MAX(0,(Inputs!B3 - Inputs!B7*(B1-Inputs!B2))) -> 710
A3: Revenue | B3: =B1*B2 -> 100414.29
A4: Total Cost | B4: =Inputs!B6 + (Inputs!B5 * B2) -> 48400
A5: Profit | B5: =MAX(0,(Inputs!B3 - Inputs!B7*(B1-Inputs!B2)))*(B1-Inputs!B5) - Inputs!B6 -> 52014.286

Sheet Simulations
A1: Simulations | B1: Price | C1: Demand | D1: Revenue | E1: Cost | F1: Profit
A2: =1 -> 1 | B2: =Model!B1 -> 141.42857 | C2: =Model!B2*(1+(RAND()-0.5)*0.2) -> 739.2093 | D2: =B2*C2 -> 104545.32 | E2: =Inputs!B6 + (Inputs!B5*(1+(RAND()-0.5)*0.1)*C2) -> 49801.5 | F2: =D2-E2 -> 54743.815
A3: =A2+1 -> 2 | B3: =Model!B2 -> 710 | C3: =Model!B3*(1+(RAND()-0.5)*0.2) -> 98992.967 | D3: =B3*C3 -> 70285006 | E3: =Inputs!B7 + (Inputs!B6*(1+(RAND()-0.5)*0.1)*C3) -> 1.9925333e+09 | F3: =D3-E3 -> -1.9222483e+09 | H3: Avg Profit | I3: =AVERAGE(F2:F501) -> 11471845
A4: =A3+1 -> 3 | B4: =Model!B3 -> 100414.29 | C4: =Model!B4*(1+(RAND()-0.5)*0.2) -> 50221.326 | D4: =B4*C4 -> 5.0429386e+09 | E4: =Inputs!B8 + (Inputs!B7*(1+(RAND()-0.5)*0.1)*C4) -> 368699.84 | F4: =D4-E4 -> 5.0425699e+09 | H4: Min Profit | I4: =MIN(F2:F501) -> -1.9222483e+09
A5: =A4+1 -> 4 | B5: =Model!B4 -> 48400 | C5: =Model!B5*(1+(RAND()-0.5)*0.2) -> 54040.214 | D5: =B5*C5 -> 2.6155463e+09 | E5: =Inputs!B9 + (Inputs!B8*(1+(RAND()-0.5)*0.1)*C5) -> 0 | F5: =D5-E5 -> 2.6155463e+09 | H5: Max Profit | I5: =MAX(F2:F501) -> 5.0425699e+09
A6: =A5+1 -> 5 | B6: =Model!B5 -> 52014.286 | C6: =Model!B6*(1+(RAND()-0.5)*0.2) -> 0 | D6: =B6*C6 -> 0 | E6: =Inputs!B10 + (Inputs!B9*(1+(RAND()-0.5)*0.1)*C6) -> 0 | F6: =D6-E6 -> 0 | H6: Risk | I6: =COUNTIF(F2:F501,"<0")/500 -> 0.002
A7: =A6+1 -> 6 | B7: =Model!B6 -> 0 | C7: =Model!B7*(1+(RAND()-0.5)*0.2) -> 0 | D7: =B7*C7 -> 0 | E7: =Inputs!B11 + (Inputs!B10*(1+(RAND()-0.5)*0.1)*C7) -> 0 | F7: =D7-E7 -> 0
A8: =A7+1 -> 7 | B8: =Model!B7 -> 0 | C8: =Model!B8*(1+(RAND()-0.5)*0.2) -> 0 | D8: =B8*C8 -> 0 | E8: =Inputs!B12 + (Inputs!B11*(1+(RAND()-0.5)*0.1)*C8) -> 0 | F8: =D8-E8 -> 0
A9: =A8+1 -> 8 | B9: =Model!B8 -> 0 | C9: =Model!B9*(1+(RAND()-0.5)*0.2) -> 0 | D9: =B9*C9 -> 0 | E9: =Inputs!B13 + (Inputs!B12*(1+(RAND()-0.5)*0.1)*C9) -> 0 | F9: =D9-E9 -> 0
A10: =A9+1 -> 9 | B10: =Model!B9 -> 0 | C10: =Model!B10*(1+(RAND()-0.5)*0.2) -> 0 | D10: =B10*C10 -> 0 | E10: =Inputs!B14 + (Inputs!B13*(1+(RAND()-0.5)*0.1)*C10) -> 0 | F10: =D10-E10 -> 0
A11: =A10+1 -> 10 | B11: =Model!B10 -> 0 | C11: =Model!B11*(1+(RAND()-0.5)*0.2) -> 0 | D11: =B11*C11 -> 0 | E11: =Inputs!B15 + (Inputs!B14*(1+(RAND()-0.5)*0.1)*C11) -> 0 | F11: =D11-E11 -> 0
A12: =A11+1 -> 11 | B12: =Model!B11 -> 0 | C12: =Model!B12*(1+(RAND()-0.5)*0.2) -> 0 | D12: =B12*C12 -> 0 | E12: =Inputs!B16 + (Inputs!B15*(1+(RAND()-0.5)*0.1)*C12) -> 0 | F12: =D12-E12 -> 0
A13: =A12+1 -> 12 | B13: =Model!B12 -> 0 | C13: =Model!B13*(1+(RAND()-0.5)*0.2) -> 0 | D13: =B13*C13 -> 0 | E13: =Inputs!B17 + (Inputs!B16*(1+(RAND()-0.5)*0.1)*C13) -> 0 | F13: =D13-E13 -> 0
A14: =A13+1 -> 13 | B14: =Model!B13 -> 0 | C14: =Model!B14*(1+(RAND()-0.5)*0.2) -> 0 | D14: =B14*C14 -> 0 | E14: =Inputs!B18 + (Inputs!B17*(1+(RAND()-0.5)*0.1)*C14) -> 0 | F14: =D14-E14 -> 0
A15: =A14+1 -> 14 | B15: =Model!B14 -> 0 | C15: =Model!B15*(1+(RAND()-0.5)*0.2) -> 0 | D15: =B15*C15 -> 0 | E15: =Inputs!B19 + (Inputs!B18*(1+(RAND()-0.5)*0.1)*C15) -> 0 | F15: =D15-E15 -> 0
A16: =A15+1 -> 15 | B16: =Model!B15 -> 0 | C16: =Model!B16*(1+(RAND()-0.5)*0.2) -> 0 | D16: =B16*C16 -> 0 | E16: =Inputs!B20 + (Inputs!B19*(1+(RAND()-0.5)*0.1)*C16) -> 0 | F16: =D16-E16 -> 0
A17: =A16+1 -> 16 | B17: =Model!B16 -> 0 | C17: =Model!B17*(1+(RAND()-0.5)*0.2) -> 0 | D17: =B17*C17 -> 0 | E17: =Inputs!B21 + (Inputs!B20*(1+(RAND()-0.5)*0.1)*C17) -> 0 | F17: =D17-E17 -> 0
A18: =A17+1 -> 17 | B18: =Model!B17 -> 0 | C18: =Model!B18*(1+(RAND()-0.5)*0.2) -> 0 | D18: =B18*C18 -> 0 | E18: =Inputs!B22 + (Inputs!B21*(1+(RAND()-0.5)*0.1)*C18) -> 0 | F18: =D18-E18 -> 0
... A501: =A500+1 -> 500 | B501: =Model!B500 -> 0 | C501: =Model!B501*(1+(RAND()-0.5)*0.2) -> 0 | D501: =B501*C501 -> 0 | E501: =Inputs!B505 + (Inputs!B504*(1+(RAND()-0.5)*0.1)*C501) -> 0 | F501: =D501-E501 -> 0

Sheet Sensitivity
A1: Price | B1: Profit
A2: 80 | B2: =MAX(0, (MAX(0, Inputs!$B$3 - Inputs!$B$7 * (A2 - Inputs!$B$2)) * (A2 - Inputs!$B$5)) - Inputs!$B$6) -> 25600
A3: 90 | B3: =MAX(0, (MAX(0, Inputs!$B$3 - Inputs!$B$7 * (A3 - Inputs!$B$2)) * (A3 - Inputs!$B$5)) - Inputs!$B$6) -> 33500
A4: 100 | B4: =MAX(0, (MAX(0, Inputs!$B$3 - Inputs!$B$7 * (A4 - Inputs!$B$2)) * (A4 - Inputs!$B$5)) - Inputs!$B$6) -> 40000 | D4: Max Profit | E4: =MAX(B2:B10) -> 51100
A5: 105 | B5: =MAX(0, (MAX(0, Inputs!$B$3 - Inputs!$B$7 * (A5 - Inputs!$B$2)) * (A5 - Inputs!$B$5)) - Inputs!$B$6) -> 42725 | D5: Co-Price | E5: =INDEX(A2:A10, MATCH(MAX(B2:B10), B2:B10, 0)) -> 130
A6: 110 | B6: =MAX(0, (MAX(0, Inputs!$B$3 - Inputs!$B$7 * (A6 - Inputs!$B$2)) * (A6 - Inputs!$B$5)) - Inputs!$B$6) -> 45100
A7: 115 | B7: =MAX(0, (MAX(0, Inputs!$B$3 - Inputs!$B$7 * (A7 - Inputs!$B$2)) * (A7 - Inputs!$B$5)) - Inputs!$B$6) -> 47125
A8: 120 | B8: =MAX(0, (MAX(0, Inputs!$B$3 - Inputs!$B$7 * (A8 - Inputs!$B$2)) * (A8 - Inputs!$B$5)) - Inputs!$B$6) -> 48800
A9: 125 | B9: =MAX(0, (MAX(0, Inputs!$B$3 - Inputs!$B$7 * (A9 - Inputs!$B$2)) * (A9 - Inputs!$B$5)) - Inputs!$B$6) -> 50125
A10: 130 | B10: =MAX(0, (MAX(0, Inputs!$B$3 - Inputs!$B$7 * (A10 - Inputs!$B$2)) * (A10 - Inputs!$B$5)) - Inputs!$B$6) -> 51100
